cur_rules/__init__.py
cur_rules/main.py
cur_rules/resources/.cursorignore
cur_rules/resources/.cursor/rules/rule.mdc
cur_rules-1.4.0.dist-info/METADATA
cur_rules-1.4.0.dist-info/WHEEL
cur_rules-1.4.0.dist-info/entry_points.txt
cur_rules-1.4.0.dist-info/top_level.txt
cur_rules-1.4.0.dist-info/RECORD
