Metadata-Version: 2.4
Name: cur_rules
Version: 1.4.0
Summary: cursor rules
Author-email: sleeping-in-bed <nyanyanyaworld@gmail.com>
Classifier: Programming Language :: Python
Classifier: Programming Language :: Python :: 3 :: Only
Classifier: Programming Language :: Python :: 3.10
Classifier: Programming Language :: Python :: 3.11
Classifier: Programming Language :: Python :: 3.12
Classifier: Programming Language :: Python :: 3.13
Classifier: Operating System :: OS Independent
Requires-Python: >=3.10
Requires-Dist: click>=8.2.0
